chatter_sdk/__init__.py
chatter_sdk/chatter.py
chatter_sdk/chatter/__init__.py
chatter_sdk/chatter/chatter.py
chatter_sdk/chatterfile/__init__.py
chatter_sdk/chatterfile/chatterfile.py
chatter_sdk/chatterfile/prompt_utils.py
chatter_sdk/chatterfile/run_utils.py
chatter_sdk-0.4.6.dist-info/METADATA
chatter_sdk-0.4.6.dist-info/WHEEL
chatter_sdk-0.4.6.dist-info/top_level.txt
chatter_sdk-0.4.6.dist-info/RECORD
